{"version":2,"kind":"Article","sha256":"1fd31efb11f1ea66aa78410dbe3fc3e6232c23454ababa238e0a45b9f3c2e3b9","slug":"coding-elements-matlab","location":"/1_prog-basics/coding-elements-MATLAB.md","dependencies":[],"frontmatter":{"title":"Necessary Coding Elements -- MATLAB","content_includes_title":false,"numbering":{"title":{"offset":1}},"exports":[{"format":"md","filename":"coding-elements-MATLAB.md","url":"/coding-elements-MATL-4b693b6c2fd2213c8a42f7974e578727.md"}]},"mdast":{"type":"root","children":[{"type":"block","children":[{"type":"paragraph","position":{"start":{"line":3,"column":1},"end":{"line":3,"column":1}},"children":[{"type":"text","value":"MATLAB is the default option for MCEN 3030 and has been the (one) language used for this class since before my time. We are opening the door to other languages, but I still expect MATLAB, which is tightly intertwined with engineering education, will have the greatest number of users in this class.","position":{"start":{"line":3,"column":1},"end":{"line":3,"column":1}},"key":"ly46qN0lEc"}],"key":"s3o6d1Edpb"},{"type":"paragraph","position":{"start":{"line":5,"column":1},"end":{"line":5,"column":1}},"children":[{"type":"text","value":"MATLAB is made for math, so, for example, the solution to “the linear algebra problem” ","position":{"start":{"line":5,"column":1},"end":{"line":5,"column":1}},"key":"iCJRvdDIi5"},{"type":"inlineMath","value":"\\mathbf{A}\\cdot\\mathbf{x}=\\mathbf{b}","position":{"start":{"line":5,"column":1},"end":{"line":5,"column":1}},"html":"<span class=\"katex\"><span class=\"katex-mathml\"><math xmlns=\"http://www.w3.org/1998/Math/MathML\"><semantics><mrow><mi mathvariant=\"bold\">A</mi><mo>⋅</mo><mi mathvariant=\"bold\">x</mi><mo>=</mo><mi mathvariant=\"bold\">b</mi></mrow><annotation encoding=\"application/x-tex\">\\mathbf{A}\\cdot\\mathbf{x}=\\mathbf{b}</annotation></semantics></math></span><span class=\"katex-html\" aria-hidden=\"true\"><span class=\"base\"><span class=\"strut\" style=\"height:0.6861em;\"></span><span class=\"mord mathbf\">A</span><span class=\"mspace\" style=\"margin-right:0.2222em;\"></span><span class=\"mbin\">⋅</span><span class=\"mspace\" style=\"margin-right:0.2222em;\"></span></span><span class=\"base\"><span class=\"strut\" style=\"height:0.4444em;\"></span><span class=\"mord mathbf\">x</span><span class=\"mspace\" style=\"margin-right:0.2778em;\"></span><span class=\"mrel\">=</span><span class=\"mspace\" style=\"margin-right:0.2778em;\"></span></span><span class=\"base\"><span class=\"strut\" style=\"height:0.6944em;\"></span><span class=\"mord mathbf\">b</span></span></span></span>","key":"xI50nj4JKV"},{"type":"text","value":" is ","position":{"start":{"line":5,"column":1},"end":{"line":5,"column":1}},"key":"yT5dg2CELE"},{"type":"inlineCode","value":"b=inv(A)*x","position":{"start":{"line":5,"column":1},"end":{"line":5,"column":1}},"key":"DjpBNw6J0n"},{"type":"text","value":" or ","position":{"start":{"line":5,"column":1},"end":{"line":5,"column":1}},"key":"hzJOlSO0hT"},{"type":"inlineCode","value":"b=A\\x","position":{"start":{"line":5,"column":1},"end":{"line":5,"column":1}},"key":"wgL2vjQsvJ"},{"type":"text","value":".","position":{"start":{"line":5,"column":1},"end":{"line":5,"column":1}},"key":"uTRUPCYPh8"}],"key":"G6S5FY33XQ"},{"type":"heading","depth":2,"position":{"start":{"line":7,"column":1},"end":{"line":7,"column":1}},"children":[{"type":"text","value":"Functions","position":{"start":{"line":7,"column":1},"end":{"line":7,"column":1}},"key":"zvIUBsNGSK"}],"identifier":"functions","label":"Functions","html_id":"functions","implicit":true,"key":"iM2aNzsJyc"},{"type":"paragraph","position":{"start":{"line":9,"column":1},"end":{"line":9,"column":1}},"children":[{"type":"text","value":"Let’s just give an example and talk about it. Here are the contents of one file, with a “local function” included below it (described below).","position":{"start":{"line":9,"column":1},"end":{"line":9,"column":1}},"key":"CLTBXH15zw"}],"key":"av7KbI2x3a"},{"type":"code","lang":"matlab","value":"function [out1,out2]=my_fxn(in1,in2)\n    x=[in1,in2];\n    out1=my_local_fxn(x);\n    out2=in2+3;\nend\n\nfunction b=my_local_fxn(x)\n    b=mean(x);\nend","position":{"start":{"line":10,"column":1},"end":{"line":20,"column":1}},"key":"Ob6yu3iBgw"},{"type":"paragraph","position":{"start":{"line":21,"column":1},"end":{"line":21,"column":1}},"children":[{"type":"text","value":"And here are a few things that you might try in a separate script file, or as an input in the command window:","position":{"start":{"line":21,"column":1},"end":{"line":21,"column":1}},"key":"uRHE4LH4ZA"}],"key":"Sj4i9Ph8VK"},{"type":"code","lang":"matlab","value":"my_fxn(4,5)\n\na=my_fxn(4,5)\n\n[a,b]=my_fxn(4,5)\n\nmy_local_fxn([4,5,6])\n","position":{"start":{"line":22,"column":1},"end":{"line":31,"column":1}},"key":"IjLmwzrDlc"},{"type":"paragraph","position":{"start":{"line":33,"column":1},"end":{"line":33,"column":1}},"children":[{"type":"text","value":"Some things you will notice:","position":{"start":{"line":33,"column":1},"end":{"line":33,"column":1}},"key":"WFS0RQDsWR"}],"key":"CZeKXdwa7F"},{"type":"list","ordered":false,"spread":false,"position":{"start":{"line":34,"column":1},"end":{"line":38,"column":1}},"children":[{"type":"listItem","spread":true,"position":{"start":{"line":34,"column":1},"end":{"line":34,"column":1}},"children":[{"type":"paragraph","children":[{"type":"inlineCode","value":"my_fxn(4,5)","position":{"start":{"line":34,"column":1},"end":{"line":34,"column":1}},"key":"SeETuVajTV"},{"type":"text","value":" works, but produces only one output. ","position":{"start":{"line":34,"column":1},"end":{"line":34,"column":1}},"key":"GMHZYGAQQp"},{"type":"inlineCode","value":"a=my_fxn(4,5)","position":{"start":{"line":34,"column":1},"end":{"line":34,"column":1}},"key":"Y89QTpKNB9"},{"type":"text","value":" works, but you only get the first output (saved as ","position":{"start":{"line":34,"column":1},"end":{"line":34,"column":1}},"key":"RpOVZ9OJxs"},{"type":"inlineCode","value":"a","position":{"start":{"line":34,"column":1},"end":{"line":34,"column":1}},"key":"Y0bnhwu9sM"},{"type":"text","value":").","position":{"start":{"line":34,"column":1},"end":{"line":34,"column":1}},"key":"DBQ9YUnKhC"}],"key":"KzIRcK944i"}],"key":"DnMRx8BPVH"},{"type":"listItem","spread":true,"position":{"start":{"line":35,"column":1},"end":{"line":35,"column":1}},"children":[{"type":"paragraph","children":[{"type":"text","value":"To get both outputs, you must “warn” MATLAB that two are coming. So the second command, ","position":{"start":{"line":35,"column":1},"end":{"line":35,"column":1}},"key":"PAQehey1jP"},{"type":"inlineCode","value":"[a,b]=my_fxn(4,5)","position":{"start":{"line":35,"column":1},"end":{"line":35,"column":1}},"key":"hEg5iPp6vW"},{"type":"text","value":" is how to get both outputs.","position":{"start":{"line":35,"column":1},"end":{"line":35,"column":1}},"key":"evN1BCwcCc"}],"key":"X0hJaOlfea"}],"key":"gYthHeb9CS"},{"type":"listItem","spread":true,"position":{"start":{"line":36,"column":1},"end":{"line":36,"column":1}},"children":[{"type":"paragraph","children":[{"type":"inlineCode","value":"my_local_fxn([4,5,6])","position":{"start":{"line":36,"column":1},"end":{"line":36,"column":1}},"key":"nnhtgW09yz"},{"type":"text","value":" produces an error: ","position":{"start":{"line":36,"column":1},"end":{"line":36,"column":1}},"key":"Ly4qXjIOi8"},{"type":"inlineCode","value":"Unrecognized function or variable 'my_local_function'.","position":{"start":{"line":36,"column":1},"end":{"line":36,"column":1}},"key":"ZZC4YQ1VhX"}],"key":"vImBsnVGc4"}],"key":"uq6XeuhD9O"},{"type":"listItem","spread":true,"position":{"start":{"line":37,"column":1},"end":{"line":38,"column":1}},"children":[{"type":"paragraph","children":[{"type":"text","value":"When calling a function, the output variables don’t need to be the same as those in the function declaration. Here: ","position":{"start":{"line":37,"column":1},"end":{"line":37,"column":1}},"key":"THCQHnZhv9"},{"type":"inlineCode","value":"a","position":{"start":{"line":37,"column":1},"end":{"line":37,"column":1}},"key":"YrmhIxaOnd"},{"type":"text","value":" and ","position":{"start":{"line":37,"column":1},"end":{"line":37,"column":1}},"key":"qFfEFvzaPi"},{"type":"inlineCode","value":"b","position":{"start":{"line":37,"column":1},"end":{"line":37,"column":1}},"key":"Yl6zquRNbi"},{"type":"text","value":" are perfectly fine names -- we don’t need to save them as ","position":{"start":{"line":37,"column":1},"end":{"line":37,"column":1}},"key":"QQUEx4JJ0G"},{"type":"inlineCode","value":"out1","position":{"start":{"line":37,"column":1},"end":{"line":37,"column":1}},"key":"xbg7msXcQq"},{"type":"text","value":" and ","position":{"start":{"line":37,"column":1},"end":{"line":37,"column":1}},"key":"QFdCXof7Jx"},{"type":"inlineCode","value":"out2","position":{"start":{"line":37,"column":1},"end":{"line":37,"column":1}},"key":"rKaSO6Egwc"},{"type":"text","value":".","position":{"start":{"line":37,"column":1},"end":{"line":37,"column":1}},"key":"IKr1JIUbaY"}],"key":"OY0Y4HPvvN"}],"key":"CvoaSpm09Y"}],"key":"nFaNt37fTl"},{"type":"paragraph","position":{"start":{"line":39,"column":1},"end":{"line":39,"column":1}},"children":[{"type":"text","value":"The Rules:","position":{"start":{"line":39,"column":1},"end":{"line":39,"column":1}},"key":"y7kRToejqq"}],"key":"YKqtYsEI6T"},{"type":"list","ordered":false,"spread":false,"position":{"start":{"line":40,"column":1},"end":{"line":45,"column":1}},"children":[{"type":"listItem","spread":true,"position":{"start":{"line":40,"column":1},"end":{"line":40,"column":1}},"children":[{"type":"paragraph","children":[{"type":"text","value":"Callable functions must have, as their first line, ","position":{"start":{"line":40,"column":1},"end":{"line":40,"column":1}},"key":"YJILsu1eXf"},{"type":"inlineCode","value":"[output variables] = function_name(input variables)","position":{"start":{"line":40,"column":1},"end":{"line":40,"column":1}},"key":"X7NP2twRSn"},{"type":"text","value":", and the file must be called ","position":{"start":{"line":40,"column":1},"end":{"line":40,"column":1}},"key":"CkhMHRuikd"},{"type":"inlineCode","value":"function name.m","position":{"start":{"line":40,"column":1},"end":{"line":40,"column":1}},"key":"QpprT6o2P7"},{"type":"text","value":".","position":{"start":{"line":40,"column":1},"end":{"line":40,"column":1}},"key":"Vzaik0wyw8"}],"key":"K39JfdfzZ6"}],"key":"qtwvTjCy9D"},{"type":"listItem","spread":true,"position":{"start":{"line":41,"column":1},"end":{"line":41,"column":1}},"children":[{"type":"paragraph","children":[{"type":"text","value":"Such functions can be called as long as you are in the same working directory -- if that ","position":{"start":{"line":41,"column":1},"end":{"line":41,"column":1}},"key":"EhY9DIvYM8"},{"type":"inlineCode","value":"*.m","position":{"start":{"line":41,"column":1},"end":{"line":41,"column":1}},"key":"vOv6m7WY0U"},{"type":"text","value":" file is in the folder you currently have open in MATLAB.","position":{"start":{"line":41,"column":1},"end":{"line":41,"column":1}},"key":"stN5XrCJK0"}],"key":"KXHRx5nqyh"}],"key":"CbBKbxRoN9"},{"type":"listItem","spread":true,"position":{"start":{"line":42,"column":1},"end":{"line":42,"column":1}},"children":[{"type":"paragraph","children":[{"type":"text","value":"The local function ","position":{"start":{"line":42,"column":1},"end":{"line":42,"column":1}},"key":"fFB6ce1tFw"},{"type":"inlineCode","value":"my_local_fxn","position":{"start":{"line":42,"column":1},"end":{"line":42,"column":1}},"key":"VfCTNaM6Wt"},{"type":"text","value":" cannot be called outside of the file. We can’t call it from a script or other function or the command window -- it is only known “locally” within the main function file ","position":{"start":{"line":42,"column":1},"end":{"line":42,"column":1}},"key":"KFg1sQLO4c"},{"type":"inlineCode","value":"my_fxn.m","position":{"start":{"line":42,"column":1},"end":{"line":42,"column":1}},"key":"Rja3ldUmN7"},{"type":"text","value":". Local functions are useful if there is a little side quest you need to do within a main function that gets rid of some clutter.","position":{"start":{"line":42,"column":1},"end":{"line":42,"column":1}},"key":"uc29K8Oz0x"}],"key":"N5KOSgJq3I"}],"key":"JEZmrJvgfz"},{"type":"listItem","spread":true,"position":{"start":{"line":43,"column":1},"end":{"line":43,"column":1}},"children":[{"type":"paragraph","children":[{"type":"text","value":"A consequence of the above: there is only one “main” function per ","position":{"start":{"line":43,"column":1},"end":{"line":43,"column":1}},"key":"HkqKKqlViS"},{"type":"inlineCode","value":"*.m","position":{"start":{"line":43,"column":1},"end":{"line":43,"column":1}},"key":"iJoKUdxfQj"},{"type":"text","value":" file. This is one of the most annoying things about MATLAB.","position":{"start":{"line":43,"column":1},"end":{"line":43,"column":1}},"key":"R0FwDgriSf"}],"key":"gL8tuUs5On"}],"key":"QD3jl927CW"},{"type":"listItem","spread":true,"position":{"start":{"line":44,"column":1},"end":{"line":45,"column":1}},"children":[{"type":"paragraph","children":[{"type":"text","value":"By default, MATLAB only returns the first output if you simply call the function. In order to retrieve the other output variables, you need to “warn” MATLAB that more are coming by defining variables where they will be stored.","position":{"start":{"line":44,"column":1},"end":{"line":44,"column":1}},"key":"M7SJcURgqS"}],"key":"qWQ11uerjs"}],"key":"f3bGRXEtzm"}],"key":"ADxR7RTygf"},{"type":"heading","depth":2,"position":{"start":{"line":46,"column":1},"end":{"line":46,"column":1}},"children":[{"type":"text","value":"Creating vectors/matrices/arrays","position":{"start":{"line":46,"column":1},"end":{"line":46,"column":1}},"key":"IFE4v2mMBj"}],"identifier":"creating-vectors-matrices-arrays","label":"Creating vectors/matrices/arrays","html_id":"creating-vectors-matrices-arrays","implicit":true,"key":"GoQf5EHjs0"},{"type":"code","lang":"matlab","value":"x1=0:0.1:2;                 % start:step:stop\nx2=linspace(0,10,500);      % 500 points between 0 and 10\nx3=logspace(4,7,500);       % 500 log-spaced points between 10^4 and 10^7\nA=[[1,2,3];[4,5,6]];        % a matrix is an array of arrays with rows separated by ;\n\ny=zeros(1,length(x2));      % a row vector full of zeros with the same length as x2\nz=ones(1,length(x2));       % same, but full of ones\nA=zeros(4,4);               % a 4x4 matrix of zeros\nB=eye(4);                   % diagonal is full of ones, rest zero\nD=diag([5,3,1]);            % diagonal is 5,3,1, rest zero\nD2=diag([5,3,1],1);         % the first diagonal above the main is [5,3,1]... so this is a 4x4 matrix\n\nr=rand(1,5);                % a row vector with 5 random numbers, uniformly spaced between 0 and 1\nR=rand(4,4);                % same, but a 4x4 matrix","position":{"start":{"line":49,"column":1},"end":{"line":64,"column":1}},"key":"dneDVwMbSs"},{"type":"heading","depth":2,"position":{"start":{"line":67,"column":1},"end":{"line":67,"column":1}},"children":[{"type":"text","value":"Indexing and Modifying Elements","position":{"start":{"line":67,"column":1},"end":{"line":67,"column":1}},"key":"qQqBVvfp0L"}],"identifier":"indexing-and-modifying-elements","label":"Indexing and Modifying Elements","html_id":"indexing-and-modifying-elements","implicit":true,"key":"dLF2e4Zv1u"},{"type":"paragraph","position":{"start":{"line":69,"column":1},"end":{"line":69,"column":1}},"children":[{"type":"text","value":"MATLAB indexes from ","position":{"start":{"line":69,"column":1},"end":{"line":69,"column":1}},"key":"SxcBtNioCM"},{"type":"inlineCode","value":"1","position":{"start":{"line":69,"column":1},"end":{"line":69,"column":1}},"key":"euytoaQaXC"},{"type":"text","value":" and can use ","position":{"start":{"line":69,"column":1},"end":{"line":69,"column":1}},"key":"Qtw0klyt0N"},{"type":"inlineCode","value":"end","position":{"start":{"line":69,"column":1},"end":{"line":69,"column":1}},"key":"arlVCvK9SR"},{"type":"text","value":" to refer to the last index. Be careful when talking to Python folks, your “first” element might be their “zeroth”.","position":{"start":{"line":69,"column":1},"end":{"line":69,"column":1}},"key":"FHFpI9C05d"}],"key":"gucSdrfX6n"},{"type":"code","lang":"matlab","value":"x(i)=5;                     % changes the ith element of x (x would need to exist already)\nx(3:end)=0;                 % elements 3 to the end all become 0\nx(2:4)=-88;                 % the second, third, and fourth elements become -88\n\nA(4,1)=5;                   % change the fourth element in column 1\nA(:,5)=6;                   % the fifth column is a vector... this makes all those elements equal 6\nA(4,:)=-9;                  % the fourth row is now full of -9s","position":{"start":{"line":71,"column":1},"end":{"line":79,"column":1}},"key":"NJcCahiqnA"},{"type":"heading","depth":2,"position":{"start":{"line":81,"column":1},"end":{"line":81,"column":1}},"children":[{"type":"text","value":"Doing math with them","position":{"start":{"line":81,"column":1},"end":{"line":81,"column":1}},"key":"pIdeZzYn6t"}],"identifier":"doing-math-with-them","label":"Doing math with them","html_id":"doing-math-with-them","implicit":true,"key":"Yar7pMK5jA"},{"type":"paragraph","position":{"start":{"line":83,"column":1},"end":{"line":83,"column":1}},"children":[{"type":"text","value":"MATLAB uses “dot star” ","position":{"start":{"line":83,"column":1},"end":{"line":83,"column":1}},"key":"epoJTeQaRp"},{"type":"inlineCode","value":".*","position":{"start":{"line":83,"column":1},"end":{"line":83,"column":1}},"key":"gPYBcJf2Ae"},{"type":"text","value":" and similar to do element-by-element math, which is mostly what we will be doing in this class.","position":{"start":{"line":83,"column":1},"end":{"line":83,"column":1}},"key":"uUh5KSmyEY"}],"key":"jCDIEVqYCM"},{"type":"code","lang":"matlab","value":"x=[1, 2, 3];\ny=[4, 5, 6];\nz=x.*y;","position":{"start":{"line":85,"column":1},"end":{"line":89,"column":1}},"key":"wYgAp0aQFZ"},{"type":"paragraph","position":{"start":{"line":90,"column":1},"end":{"line":90,"column":1}},"children":[{"type":"text","value":"From the above code, we would find ","position":{"start":{"line":90,"column":1},"end":{"line":90,"column":1}},"key":"mbk7PHrd36"},{"type":"inlineCode","value":"z=[4, 10, 18]","position":{"start":{"line":90,"column":1},"end":{"line":90,"column":1}},"key":"BLcuJoU9Xy"},{"type":"text","value":". To square all elements, ","position":{"start":{"line":90,"column":1},"end":{"line":90,"column":1}},"key":"dhbpa4qHpo"},{"type":"inlineCode","value":".^2","position":{"start":{"line":90,"column":1},"end":{"line":90,"column":1}},"key":"nc1oM9ZE4b"},{"type":"text","value":", to divide element-by-element, ","position":{"start":{"line":90,"column":1},"end":{"line":90,"column":1}},"key":"zOUBuh4h8j"},{"type":"inlineCode","value":"x./y","position":{"start":{"line":90,"column":1},"end":{"line":90,"column":1}},"key":"vP7r5VyLB5"},{"type":"text","value":". No dot is needed for addition and subtraction.","position":{"start":{"line":90,"column":1},"end":{"line":90,"column":1}},"key":"MEgzgnehAg"}],"key":"u7WG86MrDW"},{"type":"paragraph","position":{"start":{"line":92,"column":1},"end":{"line":92,"column":1}},"children":[{"type":"text","value":"Common mathematical functions work element-by-element on arrays: ","position":{"start":{"line":92,"column":1},"end":{"line":92,"column":1}},"key":"iSg07JhQsZ"},{"type":"inlineCode","value":"sin(x)","position":{"start":{"line":92,"column":1},"end":{"line":92,"column":1}},"key":"veojucIBU9"},{"type":"text","value":", ","position":{"start":{"line":92,"column":1},"end":{"line":92,"column":1}},"key":"na6rKbDD7t"},{"type":"inlineCode","value":"exp(x)","position":{"start":{"line":92,"column":1},"end":{"line":92,"column":1}},"key":"FyZ1A14tdi"},{"type":"text","value":", ","position":{"start":{"line":92,"column":1},"end":{"line":92,"column":1}},"key":"JrpiDB9tGa"},{"type":"inlineCode","value":"log(x)","position":{"start":{"line":92,"column":1},"end":{"line":92,"column":1}},"key":"XEc0nv6TWV"},{"type":"text","value":" is the natural log, ","position":{"start":{"line":92,"column":1},"end":{"line":92,"column":1}},"key":"kFwjFBkGwc"},{"type":"inlineCode","value":"log10(x)","position":{"start":{"line":92,"column":1},"end":{"line":92,"column":1}},"key":"k3OyeBkrCg"},{"type":"text","value":" is the base-10 log, ","position":{"start":{"line":92,"column":1},"end":{"line":92,"column":1}},"key":"W4bgoLaTbq"},{"type":"inlineCode","value":"sqrt(x)","position":{"start":{"line":92,"column":1},"end":{"line":92,"column":1}},"key":"gvaCdD5R64"},{"type":"text","value":" for square root. sin, cos, tan, etc.","position":{"start":{"line":92,"column":1},"end":{"line":92,"column":1}},"key":"OsMYKv1x4p"}],"key":"GY3yGuNEf9"},{"type":"heading","depth":2,"position":{"start":{"line":95,"column":1},"end":{"line":95,"column":1}},"children":[{"type":"text","value":"Conditional Statements","position":{"start":{"line":95,"column":1},"end":{"line":95,"column":1}},"key":"jIJHUdWcCq"}],"identifier":"conditional-statements","label":"Conditional Statements","html_id":"conditional-statements","implicit":true,"key":"T2ESrM3Sch"},{"type":"paragraph","position":{"start":{"line":96,"column":1},"end":{"line":96,"column":1}},"children":[{"type":"text","value":"Here is the ","position":{"start":{"line":96,"column":1},"end":{"line":96,"column":1}},"key":"rKvC5Gy45V"},{"type":"inlineCode","value":"if","position":{"start":{"line":96,"column":1},"end":{"line":96,"column":1}},"key":"JiAbrab3zN"},{"type":"text","value":"-","position":{"start":{"line":96,"column":1},"end":{"line":96,"column":1}},"key":"sq0lNnqmrL"},{"type":"inlineCode","value":"elseif","position":{"start":{"line":96,"column":1},"end":{"line":96,"column":1}},"key":"vg2djgGPm7"},{"type":"text","value":"-","position":{"start":{"line":96,"column":1},"end":{"line":96,"column":1}},"key":"bJ2NS9bha1"},{"type":"inlineCode","value":"else","position":{"start":{"line":96,"column":1},"end":{"line":96,"column":1}},"key":"RPzCI5NvQe"},{"type":"text","value":" structure:","position":{"start":{"line":96,"column":1},"end":{"line":96,"column":1}},"key":"SIbTsuJilB"}],"key":"YH6CnDjdNk"},{"type":"code","lang":"matlab","value":"if x<5\n    y=10;\nelseif x>9\n    y=15;\nelse\n    y=-99;\nend","position":{"start":{"line":98,"column":1},"end":{"line":106,"column":1}},"key":"C4HEUErFNF"},{"type":"paragraph","position":{"start":{"line":108,"column":1},"end":{"line":108,"column":1}},"children":[{"type":"text","value":"The “logical equals” is ","position":{"start":{"line":108,"column":1},"end":{"line":108,"column":1}},"key":"Hde3UCjSQF"},{"type":"inlineCode","value":"==","position":{"start":{"line":108,"column":1},"end":{"line":108,"column":1}},"key":"aCEJzuQwyq"},{"type":"text","value":" (as in, ","position":{"start":{"line":108,"column":1},"end":{"line":108,"column":1}},"key":"CKLyiP6Zvv"},{"type":"inlineCode","value":"x==5","position":{"start":{"line":108,"column":1},"end":{"line":108,"column":1}},"key":"o9HWlsUWZL"},{"type":"text","value":" checks to see if ","position":{"start":{"line":108,"column":1},"end":{"line":108,"column":1}},"key":"Iz1ZJnvww5"},{"type":"inlineCode","value":"x","position":{"start":{"line":108,"column":1},"end":{"line":108,"column":1}},"key":"Sbk9OCGV1E"},{"type":"text","value":" is equal to ","position":{"start":{"line":108,"column":1},"end":{"line":108,"column":1}},"key":"P2jmi76HX1"},{"type":"inlineCode","value":"5","position":{"start":{"line":108,"column":1},"end":{"line":108,"column":1}},"key":"XA19tJ2r1M"},{"type":"text","value":", evaluating that as True/False or 1/0). The logical and is ","position":{"start":{"line":108,"column":1},"end":{"line":108,"column":1}},"key":"NOrXgGVf20"},{"type":"inlineCode","value":"&&","position":{"start":{"line":108,"column":1},"end":{"line":108,"column":1}},"key":"uO2H3HeTaL"},{"type":"text","value":", the logical or is ","position":{"start":{"line":108,"column":1},"end":{"line":108,"column":1}},"key":"grljoyee4a"},{"type":"inlineCode","value":"||","position":{"start":{"line":108,"column":1},"end":{"line":108,"column":1}},"key":"SLtF0LSOr2"},{"type":"text","value":", and ","position":{"start":{"line":108,"column":1},"end":{"line":108,"column":1}},"key":"eBRwj1FKHE"},{"type":"inlineCode","value":">=","position":{"start":{"line":108,"column":1},"end":{"line":108,"column":1}},"key":"d5qtbXxMep"},{"type":"text","value":" and ","position":{"start":{"line":108,"column":1},"end":{"line":108,"column":1}},"key":"ZNCAf3Fut9"},{"type":"inlineCode","value":"<=","position":{"start":{"line":108,"column":1},"end":{"line":108,"column":1}},"key":"mNksJwItoN"},{"type":"text","value":" work as you’d expect! “Not equals” is ","position":{"start":{"line":108,"column":1},"end":{"line":108,"column":1}},"key":"XEc2HhGmTV"},{"type":"inlineCode","value":"~=","position":{"start":{"line":108,"column":1},"end":{"line":108,"column":1}},"key":"F0JXXlr9zp"},{"type":"text","value":".","position":{"start":{"line":108,"column":1},"end":{"line":108,"column":1}},"key":"AwK6nSZcWw"}],"key":"fKs13eY0sT"},{"type":"heading","depth":2,"position":{"start":{"line":110,"column":1},"end":{"line":110,"column":1}},"children":[{"type":"text","value":"Loops","position":{"start":{"line":110,"column":1},"end":{"line":110,"column":1}},"key":"DRQDSRlWed"}],"identifier":"loops","label":"Loops","html_id":"loops","implicit":true,"key":"u03ke1eBNc"},{"type":"paragraph","position":{"start":{"line":111,"column":1},"end":{"line":111,"column":1}},"children":[{"type":"text","value":"A ","position":{"start":{"line":111,"column":1},"end":{"line":111,"column":1}},"key":"rrm3BsZFfY"},{"type":"inlineCode","value":"while","position":{"start":{"line":111,"column":1},"end":{"line":111,"column":1}},"key":"CH6nSH4G29"},{"type":"text","value":" loop looks like this:","position":{"start":{"line":111,"column":1},"end":{"line":111,"column":1}},"key":"C8NigKELV4"}],"key":"Lxlsbl91Jz"},{"type":"code","lang":"matlab","value":"counter=0;\nwhile counter<5\n    display('hi')\n    counter=counter+1;\nend","position":{"start":{"line":112,"column":1},"end":{"line":118,"column":1}},"key":"zIkGyP16Vh"},{"type":"paragraph","position":{"start":{"line":120,"column":1},"end":{"line":120,"column":1}},"children":[{"type":"text","value":"and a ","position":{"start":{"line":120,"column":1},"end":{"line":120,"column":1}},"key":"MtgzrGd4Er"},{"type":"inlineCode","value":"for","position":{"start":{"line":120,"column":1},"end":{"line":120,"column":1}},"key":"XtSfHwJrmn"},{"type":"text","value":" loop looks like this:","position":{"start":{"line":120,"column":1},"end":{"line":120,"column":1}},"key":"Pp9Sb8reoZ"}],"key":"QSjm7lKhiI"},{"type":"code","lang":"matlab","value":"x=[1,2,3];\nS=0;\nfor i=1:length(x)\n    S=S+x(i);\nend","position":{"start":{"line":121,"column":1},"end":{"line":127,"column":1}},"key":"IgbPfJ4gdk"},{"type":"heading","depth":2,"position":{"start":{"line":129,"column":1},"end":{"line":129,"column":1}},"children":[{"type":"text","value":"Reading/Writing Spreadsheets","position":{"start":{"line":129,"column":1},"end":{"line":129,"column":1}},"key":"yM9YrgWAq4"}],"identifier":"reading-writing-spreadsheets","label":"Reading/Writing Spreadsheets","html_id":"reading-writing-spreadsheets","implicit":true,"key":"afQz2B1t3D"},{"type":"paragraph","position":{"start":{"line":131,"column":1},"end":{"line":131,"column":1}},"children":[{"type":"text","value":"It is common to use ","position":{"start":{"line":131,"column":1},"end":{"line":131,"column":1}},"key":"G2ed6eYglp"},{"type":"inlineCode","value":"*.csv","position":{"start":{"line":131,"column":1},"end":{"line":131,"column":1}},"key":"pDhhemqwIC"},{"type":"text","value":" files: comma-separated values. You may be able to load from other sources, but csv will be our standard because of the predictability of the formatting.","position":{"start":{"line":131,"column":1},"end":{"line":131,"column":1}},"key":"G1YdEVNIsR"}],"key":"LN46gsVcvB"},{"type":"paragraph","position":{"start":{"line":133,"column":1},"end":{"line":133,"column":1}},"children":[{"type":"text","value":"To read in a csv and store the data as a matrix: ","position":{"start":{"line":133,"column":1},"end":{"line":133,"column":1}},"key":"wNLpBPEWOu"},{"type":"inlineCode","value":"data = readmatrix('my_data.csv');","position":{"start":{"line":133,"column":1},"end":{"line":133,"column":1}},"key":"hvh2MUgeSa"},{"type":"text","value":". (From there you can get individual columns via ","position":{"start":{"line":133,"column":1},"end":{"line":133,"column":1}},"key":"l2rNOwUaup"},{"type":"inlineCode","value":"x_data=data(:,1)","position":{"start":{"line":133,"column":1},"end":{"line":133,"column":1}},"key":"H9x2r2vb2U"},{"type":"text","value":" etc.)","position":{"start":{"line":133,"column":1},"end":{"line":133,"column":1}},"key":"lTE3YhMLTK"}],"key":"x8OCTcRlj4"},{"type":"paragraph","position":{"start":{"line":135,"column":1},"end":{"line":135,"column":1}},"children":[{"type":"text","value":"To write a new csv: ","position":{"start":{"line":135,"column":1},"end":{"line":135,"column":1}},"key":"HS62Xn62QA"},{"type":"inlineCode","value":"writematrix([x_data, y_data], 'data.csv');","position":{"start":{"line":135,"column":1},"end":{"line":135,"column":1}},"key":"tLAbBJRUDF"},{"type":"text","value":" creates a new file in your current directory called “data.csv”.","position":{"start":{"line":135,"column":1},"end":{"line":135,"column":1}},"key":"v2cBUSJsPU"}],"key":"l9iHWD8hre"},{"type":"heading","depth":2,"position":{"start":{"line":137,"column":1},"end":{"line":137,"column":1}},"children":[{"type":"text","value":"Anonymous Functions","position":{"start":{"line":137,"column":1},"end":{"line":137,"column":1}},"key":"p4PhXKVYUy"}],"identifier":"anonymous-functions","label":"Anonymous Functions","html_id":"anonymous-functions","implicit":true,"key":"yXT8hhHKLN"},{"type":"paragraph","position":{"start":{"line":139,"column":1},"end":{"line":139,"column":1}},"children":[{"type":"text","value":"In our root-finding algorithms, we will input a (mathematical) function into a (programming) function, e.g.: find the root of ","position":{"start":{"line":139,"column":1},"end":{"line":139,"column":1}},"key":"zHuDqtpgr4"},{"type":"inlineMath","value":"f(x)=\\sin(x)-0.85","position":{"start":{"line":139,"column":1},"end":{"line":139,"column":1}},"html":"<span class=\"katex\"><span class=\"katex-mathml\"><math xmlns=\"http://www.w3.org/1998/Math/MathML\"><semantics><mrow><mi>f</mi><mo stretchy=\"false\">(</mo><mi>x</mi><mo stretchy=\"false\">)</mo><mo>=</mo><mi>sin</mi><mo>⁡</mo><mo stretchy=\"false\">(</mo><mi>x</mi><mo stretchy=\"false\">)</mo><mo>−</mo><mn>0.85</mn></mrow><annotation encoding=\"application/x-tex\">f(x)=\\sin(x)-0.85</annotation></semantics></math></span><span class=\"katex-html\" aria-hidden=\"true\"><span class=\"base\"><span class=\"strut\" style=\"height:1em;vertical-align:-0.25em;\"></span><span class=\"mord mathnormal\" style=\"margin-right:0.10764em;\">f</span><span class=\"mopen\">(</span><span class=\"mord mathnormal\">x</span><span class=\"mclose\">)</span><span class=\"mspace\" style=\"margin-right:0.2778em;\"></span><span class=\"mrel\">=</span><span class=\"mspace\" style=\"margin-right:0.2778em;\"></span></span><span class=\"base\"><span class=\"strut\" style=\"height:1em;vertical-align:-0.25em;\"></span><span class=\"mop\">sin</span><span class=\"mopen\">(</span><span class=\"mord mathnormal\">x</span><span class=\"mclose\">)</span><span class=\"mspace\" style=\"margin-right:0.2222em;\"></span><span class=\"mbin\">−</span><span class=\"mspace\" style=\"margin-right:0.2222em;\"></span></span><span class=\"base\"><span class=\"strut\" style=\"height:0.6444em;\"></span><span class=\"mord\">0.85</span></span></span></span>","key":"HPggo7CdL3"},{"type":"text","value":". This can be achieved via an anonymous function: ","position":{"start":{"line":139,"column":1},"end":{"line":139,"column":1}},"key":"ut4ps9ZB7u"},{"type":"inlineCode","value":"f=@(x) sin(x)-0.85;","position":{"start":{"line":139,"column":1},"end":{"line":139,"column":1}},"key":"na7gDOfE1C"},{"type":"text","value":".","position":{"start":{"line":139,"column":1},"end":{"line":139,"column":1}},"key":"q7q61uQNNS"}],"key":"oIZ6ds4n7u"},{"type":"paragraph","position":{"start":{"line":141,"column":1},"end":{"line":141,"column":1}},"children":[{"type":"text","value":"If two inputs are needed: ","position":{"start":{"line":141,"column":1},"end":{"line":141,"column":1}},"key":"AshAzZA5Vz"},{"type":"inlineCode","value":"f=@(x,y) x+y;","position":{"start":{"line":141,"column":1},"end":{"line":141,"column":1}},"key":"Y0uQI48EPC"},{"type":"text","value":".","position":{"start":{"line":141,"column":1},"end":{"line":141,"column":1}},"key":"SqedpwasGS"}],"key":"oX9bsrFMhp"},{"type":"heading","depth":2,"position":{"start":{"line":143,"column":1},"end":{"line":143,"column":1}},"children":[{"type":"text","value":"break, continue, and return","position":{"start":{"line":143,"column":1},"end":{"line":143,"column":1}},"key":"ddegjgTdXV"}],"identifier":"break-continue-and-return","label":"break, continue, and return","html_id":"break-continue-and-return","implicit":true,"key":"IwsMisj8Wd"},{"type":"paragraph","position":{"start":{"line":145,"column":1},"end":{"line":145,"column":1}},"children":[{"type":"text","value":"When you are within a loop, ","position":{"start":{"line":145,"column":1},"end":{"line":145,"column":1}},"key":"lZoO4IfWcn"},{"type":"inlineCode","value":"break","position":{"start":{"line":145,"column":1},"end":{"line":145,"column":1}},"key":"bnKDWA4J3q"},{"type":"text","value":" immediately breaks you out of the loop entirely. So, for example:","position":{"start":{"line":145,"column":1},"end":{"line":145,"column":1}},"key":"kZleG5DJtU"}],"key":"uFwpxXbp3H"},{"type":"code","lang":"matlab","value":"for i=1:5\n    if i==3\n        break\n    end\nend\ndisplay(i)","position":{"start":{"line":146,"column":1},"end":{"line":153,"column":1}},"key":"Nop7fAmF2g"},{"type":"paragraph","position":{"start":{"line":154,"column":1},"end":{"line":154,"column":1}},"children":[{"type":"text","value":"You should see that ","position":{"start":{"line":154,"column":1},"end":{"line":154,"column":1}},"key":"vxVrfmh2BB"},{"type":"inlineCode","value":"i","position":{"start":{"line":154,"column":1},"end":{"line":154,"column":1}},"key":"xOkZXHSYVA"},{"type":"text","value":" is 3.","position":{"start":{"line":154,"column":1},"end":{"line":154,"column":1}},"key":"HGWvyN4Xc4"}],"key":"zjAKr5xFeF"},{"type":"paragraph","position":{"start":{"line":156,"column":1},"end":{"line":156,"column":1}},"children":[{"type":"text","value":"When you are within a loop, ","position":{"start":{"line":156,"column":1},"end":{"line":156,"column":1}},"key":"IDqWqWESLg"},{"type":"inlineCode","value":"continue","position":{"start":{"line":156,"column":1},"end":{"line":156,"column":1}},"key":"Ux4o6OFwUR"},{"type":"text","value":" immediately sends you back to the top of the loop. So, for example:","position":{"start":{"line":156,"column":1},"end":{"line":156,"column":1}},"key":"WzBk7Bu1Br"}],"key":"hIP1kKNBNC"},{"type":"code","lang":"matlab","value":"S=0;\nfor i=1:5\n    if i==2 || i==3\n        continue\n    end\n    S=S+1;\nend\ndisplay(S)","position":{"start":{"line":157,"column":1},"end":{"line":166,"column":1}},"key":"Qv3actK5Do"},{"type":"paragraph","position":{"start":{"line":167,"column":1},"end":{"line":167,"column":1}},"children":[{"type":"text","value":"You should see that ","position":{"start":{"line":167,"column":1},"end":{"line":167,"column":1}},"key":"guvy9jXTny"},{"type":"inlineCode","value":"S","position":{"start":{"line":167,"column":1},"end":{"line":167,"column":1}},"key":"ubVkaDx2X9"},{"type":"text","value":" is 3.","position":{"start":{"line":167,"column":1},"end":{"line":167,"column":1}},"key":"BQ3W8Jod68"}],"key":"vpXFIt2jOH"},{"type":"paragraph","position":{"start":{"line":169,"column":1},"end":{"line":169,"column":1}},"children":[{"type":"text","value":"Anywhere within a function, a ","position":{"start":{"line":169,"column":1},"end":{"line":169,"column":1}},"key":"Rqpln65P3g"},{"type":"inlineCode","value":"return","position":{"start":{"line":169,"column":1},"end":{"line":169,"column":1}},"key":"Iuy2a96GOs"},{"type":"text","value":" functions as an ","position":{"start":{"line":169,"column":1},"end":{"line":169,"column":1}},"key":"OWHGOCrXqD"},{"type":"inlineCode","value":"end","position":{"start":{"line":169,"column":1},"end":{"line":169,"column":1}},"key":"iQfni2I2ea"},{"type":"text","value":", and outputs the current values of the output variables. So, for example:","position":{"start":{"line":169,"column":1},"end":{"line":169,"column":1}},"key":"rNtRy6649U"}],"key":"qIDiiJawn1"},{"type":"code","lang":"matlab","value":"function y=my_fxn(x)\n    if x==0\n        y=0;\n        return\n    end\n    y=15;\nend","position":{"start":{"line":170,"column":1},"end":{"line":178,"column":1}},"key":"h7dh2ZpPhE"},{"type":"paragraph","position":{"start":{"line":179,"column":1},"end":{"line":179,"column":1}},"children":[{"type":"text","value":"If you call the function with ","position":{"start":{"line":179,"column":1},"end":{"line":179,"column":1}},"key":"guqTjSvbYP"},{"type":"inlineCode","value":"my_fxn(0)","position":{"start":{"line":179,"column":1},"end":{"line":179,"column":1}},"key":"V9XNSDUCiv"},{"type":"text","value":", it should return 0. If you call it with any other number, say ","position":{"start":{"line":179,"column":1},"end":{"line":179,"column":1}},"key":"wKsebRxJlK"},{"type":"inlineCode","value":"my_fxn(1)","position":{"start":{"line":179,"column":1},"end":{"line":179,"column":1}},"key":"ubfvqSifr7"},{"type":"text","value":", it should return 15.","position":{"start":{"line":179,"column":1},"end":{"line":179,"column":1}},"key":"AMedRiZ1il"}],"key":"IpuqxtTYUF"},{"type":"heading","depth":2,"position":{"start":{"line":182,"column":1},"end":{"line":182,"column":1}},"children":[{"type":"text","value":"Some common motifs","position":{"start":{"line":182,"column":1},"end":{"line":182,"column":1}},"key":"frjuAGxkBy"}],"identifier":"some-common-motifs","label":"Some common motifs","html_id":"some-common-motifs","implicit":true,"key":"F1Jz7S9f5v"},{"type":"paragraph","position":{"start":{"line":184,"column":1},"end":{"line":184,"column":1}},"children":[{"type":"text","value":"If you need something to happen if a number is even:","position":{"start":{"line":184,"column":1},"end":{"line":184,"column":1}},"key":"kTKJ0Nf4US"}],"key":"r9HtK6KAuf"},{"type":"code","lang":"matlab","value":"if mod(x,2)==0  % even!\n    % do something\nelse            % odd!\n    % do something else\nend","position":{"start":{"line":186,"column":1},"end":{"line":192,"column":1}},"key":"MiK7LsQW7l"},{"type":"paragraph","position":{"start":{"line":195,"column":1},"end":{"line":195,"column":1}},"children":[{"type":"text","value":"To calculation a summation, initialize the sum at zero:","position":{"start":{"line":195,"column":1},"end":{"line":195,"column":1}},"key":"kn4yqGElw0"}],"key":"fFskMccgbU"},{"type":"code","lang":"matlab","value":"N=15;       % how many terms to include\nS=0;        % initialize the sum at zero\nfor n=1:N\n    S=S+sin(n);\nend","position":{"start":{"line":197,"column":1},"end":{"line":203,"column":1}},"key":"ngi27i4lfI"},{"type":"paragraph","position":{"start":{"line":205,"column":1},"end":{"line":205,"column":1}},"children":[{"type":"text","value":"MATLAB has built-in functions: ","position":{"start":{"line":205,"column":1},"end":{"line":205,"column":1}},"key":"seJdbYTNlV"},{"type":"inlineCode","value":"isnan","position":{"start":{"line":205,"column":1},"end":{"line":205,"column":1}},"key":"bCFQokoG6u"},{"type":"text","value":", which checks if a number is ","position":{"start":{"line":205,"column":1},"end":{"line":205,"column":1}},"key":"bfcM3TOG0K"},{"type":"inlineCode","value":"NaN","position":{"start":{"line":205,"column":1},"end":{"line":205,"column":1}},"key":"WGdUHPH6wp"},{"type":"text","value":" (“not a number”); and ","position":{"start":{"line":205,"column":1},"end":{"line":205,"column":1}},"key":"jNdBxkigKW"},{"type":"inlineCode","value":"isinf","position":{"start":{"line":205,"column":1},"end":{"line":205,"column":1}},"key":"rXNkbql1NZ"},{"type":"text","value":", which checks if a number is ","position":{"start":{"line":205,"column":1},"end":{"line":205,"column":1}},"key":"EvfLA7qdO8"},{"type":"inlineCode","value":"Inf","position":{"start":{"line":205,"column":1},"end":{"line":205,"column":1}},"key":"W8E1Ze7uEH"},{"type":"text","value":". ","position":{"start":{"line":205,"column":1},"end":{"line":205,"column":1}},"key":"yxqFvna9FB"},{"type":"inlineCode","value":"NaN","position":{"start":{"line":205,"column":1},"end":{"line":205,"column":1}},"key":"WlhIklf2Ky"},{"type":"text","value":" and ","position":{"start":{"line":205,"column":1},"end":{"line":205,"column":1}},"key":"Tb1It6EZ0X"},{"type":"inlineCode","value":"Inf","position":{"start":{"line":205,"column":1},"end":{"line":205,"column":1}},"key":"ZDeAaYnhaq"},{"type":"text","value":" are different in MATLAB:","position":{"start":{"line":205,"column":1},"end":{"line":205,"column":1}},"key":"R8ZlpH6819"}],"key":"ZPnHOKpSOQ"},{"type":"code","lang":"matlab","value":"isnan(15)  % returns 0 because 15 IS a number\nisnan(1/0) % returns 0 because MATLAB interprets Inf as a number\nisnan(0/0) % returns 1\nisinf(15)  % returns 0\nisinf(1/0) % returns 1\nisinf(0,0) % returns 0","position":{"start":{"line":206,"column":1},"end":{"line":213,"column":1}},"key":"GKN3oV3OXz"}],"key":"ldzYZVMAIN"}],"key":"pOQboQs9rE"},"references":{"cite":{"order":[],"data":{}}}}